smartdecision_sdk/__init__.py
smartdecision_sdk/client.py
smartdecision_sdk/exceptions.py
smartdecision_sdk/models.py
smartdecision_sdk/utils.py
smartdecision_sdk-1.0.3.dist-info/METADATA
smartdecision_sdk-1.0.3.dist-info/WHEEL
smartdecision_sdk-1.0.3.dist-info/top_level.txt
smartdecision_sdk-1.0.3.dist-info/RECORD
