Metadata-Version: 2.4
Name: smartdecision-sdk
Version: 1.0.3
Summary: Python SDK for SmartDecision AI-powered ensemble decision making
Home-page: https://github.com/ankryptonite/smartdecision-python-sdk
Author: Alex Zhang
Author-email: Alex Zhang <1108alexzhang@gmail.com>
License: MIT
Project-URL: Homepage, https://smartdecision.ai
Project-URL: Documentation, https://github.com/ankryptonite/smartdecision-python-sdk
Project-URL: Repository, https://github.com/ankryptonite/smartdecision-python-sdk
Project-URL: Bug Reports, https://github.com/smartdecision-python-sdk/issues
Keywords: ai,decision-making,ensemble,llm,machine-learning,api,sdk
Classifier: Development Status :: 4 - Beta
Classifier: Intended Audience :: Developers
Classifier: License :: OSI Approved :: MIT License
Classifier: Operating System :: OS Independent
Classifier: Programming Language :: Python :: 3
Classifier: Programming Language :: Python :: 3.8
Classifier: Programming Language :: Python :: 3.9
Classifier: Programming Language :: Python :: 3.10
Classifier: Programming Language :: Python :: 3.11
Classifier: Programming Language :: Python :: 3.12
Classifier: Topic :: Software Development :: Libraries :: Python Modules
Classifier: Topic :: Scientific/Engineering :: Artificial Intelligence
Requires-Python: >=3.8
Requires-Dist: httpx>=0.24.0
Requires-Dist: pydantic>=2.0.0
Requires-Dist: typing-extensions>=4.0.0
Provides-Extra: dev
Requires-Dist: pytest>=7.0.0; extra == "dev"
Requires-Dist: pytest-asyncio>=0.21.0; extra == "dev"
Requires-Dist: black>=22.0.0; extra == "dev"
Requires-Dist: isort>=5.0.0; extra == "dev"
Requires-Dist: flake8>=4.0.0; extra == "dev"
Requires-Dist: mypy>=0.950; extra == "dev"
Provides-Extra: docs
Requires-Dist: sphinx>=4.0.0; extra == "docs"
Requires-Dist: sphinx-rtd-theme>=1.0.0; extra == "docs"
Dynamic: author
Dynamic: home-page
Dynamic: requires-python
